itksn/__init__.py
itksn/_version.py
itksn/_version.pyi
itksn/common.py
itksn/core.py
itksn/py.typed
itksn/cli/__init__.py
itksn/cli/__main__.py
itksn/cli/main.py
itksn/pixels/__init__.py
itksn/pixels/common.py
itksn/pixels/local_supports.py
itksn/pixels/modules.py
itksn/pixels/services.py
itksn/pixels/utils.py
itksn-0.4.2.dist-info/METADATA
itksn-0.4.2.dist-info/WHEEL
itksn-0.4.2.dist-info/entry_points.txt
itksn-0.4.2.dist-info/licenses/LICENSE
itksn-0.4.2.dist-info/RECORD
