Metadata-Version: 2.4
Name: itksn
Version: 0.4.2
Summary: ITk Serial Number parser
Project-URL: Homepage, https://github.com/kratsg/itksn
Project-URL: Documentation, https://kratsg.github.io/itksn/0.4/
Project-URL: Tracker, https://github.com/kratsg/itksn/issues
Project-URL: Discussions, https://github.com/kratsg/itksn/discussions
Project-URL: Changelog, https://github.com/kratsg/itksn/releases
Author-email: Giordon Stark <kratsg@gmail.com>
License-File: LICENSE
Classifier: Development Status :: 1 - Planning
Classifier: Intended Audience :: Developers
Classifier: Intended Audience :: Science/Research
Classifier: License :: OSI Approved :: BSD License
Classifier: Operating System :: OS Independent
Classifier: Programming Language :: Python
Classifier: Programming Language :: Python :: 3
Classifier: Programming Language :: Python :: 3 :: Only
Classifier: Programming Language :: Python :: 3.8
Classifier: Programming Language :: Python :: 3.9
Classifier: Programming Language :: Python :: 3.10
Classifier: Programming Language :: Python :: 3.11
Classifier: Topic :: Scientific/Engineering
Classifier: Typing :: Typed
Requires-Python: >=3.8
Requires-Dist: construct>=2.10
Requires-Dist: typer
Requires-Dist: typing-extensions>=3.8; python_version < '3.11'
Provides-Extra: dev
Requires-Dist: pytest-cov>=3; extra == 'dev'
Requires-Dist: pytest>=6; extra == 'dev'
Provides-Extra: docs
Requires-Dist: myst-parser>=0.13; extra == 'docs'
Requires-Dist: sphinx-book-theme>=0.1.0; extra == 'docs'
Requires-Dist: sphinx-copybutton; extra == 'docs'
Requires-Dist: sphinx>=4.0; extra == 'docs'
Provides-Extra: test
Requires-Dist: pytest-cov>=3; extra == 'test'
Requires-Dist: pytest>=6; extra == 'test'
